dcmqi/__init__.py
dcmqi/_version.py
dcmqi/_version.pyi
dcmqi/bin/itkimage2paramap.exe
dcmqi/bin/itkimage2segimage.exe
dcmqi/bin/paramap2itkimage.exe
dcmqi/bin/segimage2itkimage.exe
dcmqi/bin/tid1500reader.exe
dcmqi/bin/tid1500writer.exe
dcmqi/py.typed
dcmqi-0.2.1.dist-info/METADATA
dcmqi-0.2.1.dist-info/WHEEL
dcmqi-0.2.1.dist-info/entry_points.txt
dcmqi-0.2.1.dist-info/licenses/LICENSE
dcmqi-0.2.1.dist-info/RECORD
