Metadata-Version: 2.1
Name: dcmqi
Version: 0.2.1
Summary: Python distribution of the DCMQI library collection.
Author-Email: =?utf-8?q?Leonard_N=C3=BCrnberg?= <lnuernberg@bwh.harvard.edu>
License: Copyright 2024 Leonard Nürnberg
Classifier: Development Status :: 1 - Planning
Classifier: Intended Audience :: Science/Research
Classifier: Intended Audience :: Developers
Classifier: License :: OSI Approved :: MIT License
Classifier: Operating System :: OS Independent
Classifier: Programming Language :: Python
Classifier: Programming Language :: Python :: 3
Classifier: Programming Language :: Python :: 3 :: Only
Classifier: Programming Language :: Python :: 3.8
Classifier: Programming Language :: Python :: 3.9
Classifier: Programming Language :: Python :: 3.10
Classifier: Programming Language :: Python :: 3.11
Classifier: Programming Language :: Python :: 3.12
Classifier: Topic :: Scientific/Engineering
Classifier: Typing :: Typed
Project-URL: Homepage, https://github.com/ImagingDataCommons/dcmqi-python-distributions
Project-URL: Bug tracker, https://github.com/ImagingDataCommons/dcmqi-python-distributions/issues
Project-URL: Discussions, https://github.com/ImagingDataCommons/dcmqi-python-distributions/discussions
Project-URL: Changelog, https://github.com/ImagingDataCommons/dcmqi-python-distributions/releases
Requires-Python: >=3.8
Provides-Extra: test
Provides-Extra: dev
Provides-Extra: docs
Requires-Dist: importlib_metadata>=2.0; python_version < "3.10" and extra == "test"
Requires-Dist: pytest>=6; extra == "test"
Requires-Dist: pytest-cov>=3; extra == "test"
Requires-Dist: pytest>=6; extra == "dev"
Requires-Dist: pytest-cov>=3; extra == "dev"
Requires-Dist: sphinx>=7.0; extra == "docs"
Requires-Dist: myst_parser>=0.13; extra == "docs"
Requires-Dist: sphinx_copybutton; extra == "docs"
Requires-Dist: sphinx_autodoc_typehints; extra == "docs"
Requires-Dist: furo>=2023.08.17; extra == "docs"
